hetman/__init__.py
hetman/_exceptions.py
hetman-0.1.1.dist-info/LICENSE
hetman-0.1.1.dist-info/METADATA
hetman-0.1.1.dist-info/WHEEL
hetman-0.1.1.dist-info/top_level.txt
hetman-0.1.1.dist-info/RECORD
