Metadata-Version: 2.1
Name: hetman
Version: 0.1.1
Summary: Official Python integration with Hetman.
Home-page: https://github.com/hetman-app/hetman-python
Author: yaria.pl
Author-email: dev@hetman.app
License: Apache
Requires-Python: >=3.6
License-File: LICENSE
Requires-Dist: requests
